textile/__init__.py
textile/textile.py
textile/architectures/__init__.py
textile/architectures/layers/__init__.py
textile/architectures/layers/attention/__init__.py
textile/architectures/layers/attention/attention.py
textile/data/teaser.png
textile/data/texture_368.jpg
textile/utils/__init__.py
textile/utils/create_model.py
textile/utils/dataset.py
textile/utils/image_utils.py
textile/utils/misc.py
textile_metric-0.0.10.dist-info/LICENSE
textile_metric-0.0.10.dist-info/METADATA
textile_metric-0.0.10.dist-info/WHEEL
textile_metric-0.0.10.dist-info/top_level.txt
textile_metric-0.0.10.dist-info/RECORD
