Metadata-Version: 2.1
Name: textile-metric
Version: 0.0.10
Summary: TexTile: A Differentiable Metric for Texture Tileability
Home-page: https://github.com/crp94/textile
Author: Carlos Rodriguez-Pardo
Author-email: carlos.rodriguezpardo.jimenez@gmail.com
Classifier: Programming Language :: Python :: 3
Classifier: Operating System :: OS Independent
Classifier: Development Status :: 4 - Beta
Classifier: License :: OSI Approved :: MIT License
Classifier: Topic :: Scientific/Engineering :: Image Processing
Classifier: Topic :: Scientific/Engineering :: Artificial Intelligence
License-File: LICENSE
Requires-Dist: torch >=1.2.0
Requires-Dist: torchvision >=0.17.1
Requires-Dist: einops >=0.7.0
Requires-Dist: numpy >=1.14.3
Requires-Dist: opencv-python >=2.4.11
Requires-Dist: kornia >=0.7.2
Requires-Dist: progressbar >=2.5
